[
    {
        "name": "Kende Gergely",
        "email": "kenede1@gmail.com",
        "address": "Piroska u. 56",
        "zip_code": "7763",
        "city": "Szôkéd",
        "country": "Hungary",
        "hospitals": [
            { "name": "Pécsi Irgalmasrendi Kórház" },
            { "name": "The Helios Hospital Berlin-Buch" }
        ]
    },
    {
        "name": "Balla Mihály",
        "email": "balla1@gmail.com",
        "address": "Baross tér 18",
        "zip_code": "3735",
        "city": "Alsótelekes",
        "country": "Hungary",
        "hospitals": [
            { "name": "Pécsi Irgalmasrendi Kórház" },
            { "name": "The University Hospital Duesseldorf" }
        ]
    },
    {
        "name": "Vincze Szabolcs",
        "email": "vincze1@gmail.com",
        "address": "Piroska u. 13",
        "zip_code": "7761",
        "city": "Kozármisleny",
        "country": "Hungary",
        "hospitals": [
            { "name": "Fővárosi Önkormányzat Heim Pál Gyermekkórház" },
            { "name": "The Helios Hospital Berlin-Buch" }
        ]
    },
    {
        "name": "Illés Nóra",
        "email": "illes1@gmail.com",
        "address": "Veres Pálné u. 60",
        "zip_code": "5703",
        "city": "Gyula",
        "country": "Hungary",
        "hospitals": [
            { "name": "Pécsi Irgalmasrendi Kórház" },
            {
                "name": "The University Hospital of Ludwig Maximilian University of Munich "
            }
        ]
    },
    {
        "name": "Nagy Anita",
        "email": "nagy1@gmail.com",
        "address": "Árpád fejedelem útja 8",
        "zip_code": "1139",
        "city": "Budapest",
        "country": "Hungary",
        "hospitals": [
            { "name": "Fővárosi Önkormányzat Heim Pál Gyermekkórház" },
            { "name": "Markhot Ferenc Oktatókórház és Rendelőintézet" }
        ]
    },
    {
        "name": "Matthias Mannheim",
        "email": "manheim1@gmail.com",
        "address": "Hochstrasse 90",
        "zip_code": "25994",
        "city": "Wenningstedt",
        "country": "Germany",
        "hospitals": [
            {
                "name": "The University Hospital of Ludwig Maximilian University of Munich "
            },
            {
                "name": "Miskolci Semmelweis Ignác Egészségügyi Központ és Egyetemi Oktatókórház"
            }
        ]
    },
    {
        "name": "Eleonore Schulte",
        "email": "schulte1@gmail.com",
        "address": "Charlottenstraße 47",
        "zip_code": "34480",
        "city": "Duesseldorf",
        "country": "Germany",
        "hospitals": [
            {
                "name": "Miskolci Semmelweis Ignác Egészségügyi Központ és Egyetemi Oktatókórház"
            },
            { "name": "The University Hospital Duesseldorf" }
        ]
    },
    {
        "name": "Ramona Thiel",
        "email": "thiel1@gmail.com",
        "address": "Hoheluftchaussee 51",
        "zip_code": "04611",
        "city": "Lucka",
        "country": "Germany",
        "hospitals": [
            { "name": "Szent Pantaleon Kórház Kht." },
            { "name": "Rigas Austrumu Kliniskas Universitates" }
        ]
    },
    {
        "name": "Audris Strautiņš",
        "email": "strautiņš1@gmail.com",
        "address": "Mersraga, bld. 9",
        "zip_code": "LV-3284",
        "city": "Riga",
        "country": "Latvia",
        "hospitals": [
            { "name": "Rigas Austrumu Kliniskas Universitate" },
            { "name": "Szent Pantaleon Kórház Kht." }
        ]
    },
    {
        "name": "Ella Forslund",
        "email": "forslund1@gmail.com",
        "address": "Björkvägen 70",
        "zip_code": "305 10",
        "city": "Holm",
        "country": "Swened",
        "hospitals": [
            { "name": "Karolinska University Hospital" },
            { "name": "The University Hospital Duesseldorf" }
        ]
    }
]
